souschef/160widthSR-Logo-Screen-PurpleGreen-HI-RGB1.jpg
souschef/__init__.py
souschef/dataexec.py
souschef/dataload.py
souschef/manage.py
souschef/billing/__init__.py
souschef/billing/admin.py
souschef/billing/apps.py
souschef/billing/csvexport.py
souschef/billing/factories.py
souschef/billing/models.py
souschef/billing/tests.py
souschef/billing/types.py
souschef/billing/urls.py
souschef/billing/views.py
souschef/billing/migrations/0001_initial.py
souschef/billing/migrations/0002_auto_20161122_0458.py
souschef/billing/migrations/0003_auto_20161122_0515.py
souschef/billing/migrations/0004_auto_20201030_1540.py
souschef/billing/migrations/__init__.py
souschef/billing/templates/base_billing.html
souschef/billing/templates/billing/add.html
souschef/billing/templates/billing/billing_confirm_delete.html
souschef/billing/templates/billing/list.html
souschef/billing/templates/billing/print_summary.html
souschef/billing/templates/billing/view.html
souschef/billing/templates/billing/view_orders.html
souschef/billing/templates/billing/partials/export_csv_modal.html
souschef/billing/templates/billing/partials/statistics.html
souschef/billing/templates/billing/partials/summary.html
souschef/configsamples/nginx.conf
souschef/configsamples/souschef.service
souschef/cronscripts/souschef_daily.sh
souschef/datamigration/__init__.py
souschef/datamigration/admin.py
souschef/datamigration/apps.py
souschef/datamigration/models.py
souschef/datamigration/tests.py
souschef/datamigration/views.py
souschef/datamigration/management/__init__.py
souschef/datamigration/management/commands/__init__.py
souschef/datamigration/management/commands/importaddresses.py
souschef/datamigration/management/commands/importclients.py
souschef/datamigration/management/commands/importcontactaddresses.py
souschef/datamigration/management/commands/importmeals.py
souschef/datamigration/management/commands/importorders.py
souschef/datamigration/management/commands/importrelationships.py
souschef-1.5.1.dist-info/LICENSE.txt
souschef-1.5.1.dist-info/METADATA
souschef-1.5.1.dist-info/WHEEL
souschef-1.5.1.dist-info/top_level.txt
souschef-1.5.1.dist-info/RECORD
