Metadata-Version: 2.1
Name: souschef
Version: 1.5.1
Summary: Webapp used to manage orders for meals-on-wheel delivery
Home-page: https://github.com/santropolroulant/sous-chef
Author: Santropol Roulant and Savoir Faire Linux
Author-email: info@santropolroulant.org
License: AGPL-3.0
Keywords: meals-on-wheel
Platform: UNKNOWN
Classifier: Development Status :: 4 - Beta
Classifier: Environment :: Web Environment
Classifier: Framework :: Django
Classifier: Intended Audience :: End Users/Desktop
Classifier: License :: OSI Approved :: GNU Affero General Public License v3
Classifier: Operating System :: OS Independent
Classifier: Programming Language :: JavaScript
Classifier: Programming Language :: Python :: 3
Classifier: Topic :: Internet :: WWW/HTTP :: Dynamic Content :: Content Management System
Requires-Python: >=3.7
License-File: LICENSE.txt
Requires-Dist: django-annoying <0.10.999,>=0.10
Requires-Dist: django-avatar <4.0.999,>=4.0
Requires-Dist: django-crontab <0.7.999,>=0.7.1
Requires-Dist: django-extra-views <0.9.999,>=0.9
Requires-Dist: django-filter <1.0.999,>=1.0
Requires-Dist: django-formtools <2.0.999,>=2.0
Requires-Dist: django-leaflet <0.22.999,>=0.22
Requires-Dist: django-localflavor <1.5.999,>=1.5
Requires-Dist: django-template-i18n-lint <1.2.999,>=1.2
Requires-Dist: django <1.11.999,>=1.11
Requires-Dist: factory-boy <2.8.999,>=2.8
Requires-Dist: mysqlclient <1.3.999,>=1.3
Requires-Dist: pypdf <5,>=4.2
Requires-Dist: pylabels <1.2.999,>=1.2
Requires-Dist: reportlab <3.4.999,>=3.4
Requires-Dist: rules <1.2.999,>=1.2
Requires-Dist: transifex-client <0.12.999,>=0.12
